jaml/__init__.py
jaml/hash.py
jaml/identify.py
jaml/main.py
jaml_edit-1.0.1.dist-info/LICENSE
jaml_edit-1.0.1.dist-info/METADATA
jaml_edit-1.0.1.dist-info/WHEEL
jaml_edit-1.0.1.dist-info/entry_points.txt
jaml_edit-1.0.1.dist-info/top_level.txt
jaml_edit-1.0.1.dist-info/RECORD
