Metadata-Version: 2.1
Name: jaml-edit
Version: 1.0.1
Summary: Edit your YAML files as JSON - and vice versa!
Home-page: https://github.com/markrawls/jaml
Author: Mark Rawls
Author-email: markrawls96@gmail.com
License: WTFPL
Platform: UNKNOWN
Requires-Dist: PyYAML (>=5.1.0)
